pydas/__init__.py
pydas/api.py
pydas/core.py
pydas/drivers.py
pydas/exceptions.py
pydas/session.py
pydas-0.3.6.dist-info/DESCRIPTION.rst
pydas-0.3.6.dist-info/METADATA
pydas-0.3.6.dist-info/RECORD
pydas-0.3.6.dist-info/WHEEL
pydas-0.3.6.dist-info/metadata.json
pydas-0.3.6.dist-info/top_level.txt
pydas-0.3.6.dist-info/zip-safe
