Metadata-Version: 2.0
Name: pydas
Version: 0.3.6
Summary: Upload data to a Midas Server application with Python.
Home-page: http://github.com/midasplatform/pydas
Author: Patrick Reynolds
Author-email: patrick.reynolds@kitware.com
License: Apache 2.0
Platform: UNKNOWN
Classifier: Development Status :: 5 - Production/Stable
Classifier: Intended Audience :: Developers
Classifier: Natural Language :: English
Classifier: License :: OSI Approved :: Apache Software License
Classifier: Programming Language :: Python
Classifier: Programming Language :: Python :: 2.6
Classifier: Programming Language :: Python :: 2.7
Classifier: Programming Language :: Python :: 3.2
Classifier: Programming Language :: Python :: 3.3
Classifier: Programming Language :: Python :: 3.4
Requires-Dist: requests
Requires-Dist: retrying
